{
  "data": {
    "article": {},
    "attachments": {},
    "author_id": "2008812080099672064",
    "conversation_id": "2040778271772889327",
    "created_at": "2026-04-05T14:34:14.000Z",
    "edit_controls": {
      "editable_until": "2026-04-05T15:34:14.000Z",
      "edits_remaining": 5,
      "is_edit_eligible": false
    },
    "edit_history_tweet_ids": [
      "2040800183676715373"
    ],
    "entities": {
      "mentions": [
        {
          "end": 12,
          "id": "2032033299980566528",
          "start": 0,
          "username": "rinii165892"
        },
        {
          "end": 25,
          "id": "2031715041196875776",
          "start": 13,
          "username": "wu_si114514"
        }
      ]
    },
    "geo": {},
    "id": "2040800183676715373",
    "in_reply_to_user_id": "2032033299980566528",
    "lang": "zh",
    "note_tweet": {
      "entities": {}
    },
    "possibly_sensitive": false,
    "public_metrics": {
      "bookmark_count": 0,
      "impression_count": 0,
      "like_count": 1,
      "quote_count": 0,
      "reply_count": 0,
      "retweet_count": 0
    },
    "referenced_tweets": [
      {
        "id": "2040778271772889327",
        "type": "replied_to"
      }
    ],
    "reply_settings": "everyone",
    "text": "@rinii165892 @wu_si114514 春风这一块QAQ"
  },
  "includes": {
    "media": [
      {
        "height": 1000,
        "media_key": "3_2040778267528241152",
        "public_metrics": {},
        "type": "photo",
        "url": "https://pbs.twimg.com/media/HFJNBZVboAAI8ZB.jpg",
        "width": 1000
      }
    ],
    "tweets": [
      {
        "article": {},
        "attachments": {},
        "author_id": "2008812080099672064",
        "conversation_id": "2040778271772889327",
        "created_at": "2026-04-05T14:34:14.000Z",
        "edit_controls": {
          "editable_until": "2026-04-05T15:34:14.000Z",
          "edits_remaining": 5,
          "is_edit_eligible": false
        },
        "edit_history_tweet_ids": [
          "2040800183676715373"
        ],
        "entities": {
          "mentions": [
            {
              "end": 12,
              "id": "2032033299980566528",
              "start": 0,
              "username": "rinii165892"
            },
            {
              "end": 25,
              "id": "2031715041196875776",
              "start": 13,
              "username": "wu_si114514"
            }
          ]
        },
        "geo": {},
        "id": "2040800183676715373",
        "in_reply_to_user_id": "2032033299980566528",
        "lang": "zh",
        "note_tweet": {
          "entities": {}
        },
        "possibly_sensitive": false,
        "public_metrics": {
          "bookmark_count": 0,
          "impression_count": 0,
          "like_count": 1,
          "quote_count": 0,
          "reply_count": 0,
          "retweet_count": 0
        },
        "referenced_tweets": [
          {
            "id": "2040778271772889327",
            "type": "replied_to"
          }
        ],
        "reply_settings": "everyone",
        "text": "@rinii165892 @wu_si114514 春风这一块QAQ"
      },
      {
        "article": {},
        "attachments": {
          "media_keys": [
            "3_2040778267528241152"
          ]
        },
        "author_id": "2032033299980566528",
        "context_annotations": [
          {
            "domain": {
              "description": "Brands and Companies",
              "id": "47",
              "name": "Brand"
            },
            "entity": {
              "id": "10045225402",
              "name": "X"
            }
          }
        ],
        "conversation_id": "2040778271772889327",
        "created_at": "2026-04-05T13:07:10.000Z",
        "edit_controls": {
          "editable_until": "2026-04-05T14:07:10.000Z",
          "edits_remaining": 5,
          "is_edit_eligible": true
        },
        "edit_history_tweet_ids": [
          "2040778271772889327"
        ],
        "entities": {
          "urls": [
            {
              "description": "This feature visually maps out your interactions, placing you in the center, with your closest interactions forming an inner circle, less frequent ones in the middle, and the occasional interactions in the outer circle.",
              "display_url": "infinitetweet.me/interaction-ci…",
              "end": 40,
              "expanded_url": "https://infinitetweet.me/interaction-circle?lang=zh",
              "images": [
                {
                  "height": 1884,
                  "url": "https://pbs.twimg.com/news_img/2038324114537271296/BDCA_d_l?format=jpg&name=orig",
                  "width": 3600
                },
                {
                  "height": 150,
                  "url": "https://pbs.twimg.com/news_img/2038324114537271296/BDCA_d_l?format=jpg&name=150x150",
                  "width": 150
                }
              ],
              "start": 17,
              "status": 200,
              "title": "Interaction Circle • Infinitweet",
              "unwound_url": "https://infinitetweet.me/interaction-circle?lang=zh",
              "url": "https://t.co/jNOg39qm5R"
            },
            {
              "display_url": "pic.x.com/qfU5hwOZUj",
              "end": 64,
              "expanded_url": "https://x.com/rinii165892/status/2040778271772889327/photo/1",
              "media_key": "3_2040778267528241152",
              "start": 41,
              "url": "https://t.co/qfU5hwOZUj"
            }
          ]
        },
        "geo": {},
        "id": "2040778271772889327",
        "lang": "zh",
        "note_tweet": {
          "entities": {}
        },
        "possibly_sensitive": false,
        "public_metrics": {
          "bookmark_count": 0,
          "impression_count": 516,
          "like_count": 35,
          "quote_count": 0,
          "reply_count": 15,
          "retweet_count": 1
        },
        "reply_settings": "everyone",
        "text": "我的Twitter互动圈\n\n➡️ https://t.co/jNOg39qm5R https://t.co/qfU5hwOZUj"
      }
    ],
    "users": [
      {
        "created_at": "2026-01-07T08:05:14.000Z",
        "description": "みんなとても可愛いですよ、私はみんなのことを大好きです！\n如果你觉得我的负面情绪影响到你 我向你道歉｜里推@NiaoYou83766｜提问箱在下面｜好姐姐@Sankta_AM",
        "entities": {
          "description": {
            "mentions": [
              {
                "end": 66,
                "start": 53,
                "username": "NiaoYou83766"
              },
              {
                "end": 87,
                "start": 77,
                "username": "Sankta_AM"
              }
            ]
          },
          "url": {
            "urls": [
              {
                "display_url": "ngl.link/xiaoyi0324",
                "end": 23,
                "expanded_url": "https://ngl.link/xiaoyi0324",
                "start": 0,
                "url": "https://t.co/SiMjjU6DSn"
              }
            ]
          }
        },
        "id": "2008812080099672064",
        "location": "来玩捉迷藏吧？",
        "name": "樱川由奈🏳️‍⚧️sakura",
        "pinned_tweet_id": "2040472479333052736",
        "profile_image_url": "https://pbs.twimg.com/profile_images/2039652543136194560/agP5b8Sq_normal.jpg",
        "protected": false,
        "public_metrics": {
          "followers_count": 113,
          "following_count": 92,
          "like_count": 658,
          "listed_count": 0,
          "media_count": 91,
          "tweet_count": 493
        },
        "url": "https://t.co/SiMjjU6DSn",
        "username": "Xiaoyi_0324",
        "verified": false
      },
      {
        "created_at": "2026-03-12T09:58:00.000Z",
        "description": "被当成人机了随缘回fo【寻回推u】🔪- ✰*🎀 ੈ✩🍥✰*💗 ੈ✩- 生活在互联网里！看成分互fo捏喵!/我是低龄糖逼大傻福，实在抱歉！/超级严重失眠 -12现役初中生^✟❀信徒@Fislonely_❀灵宠@dbdbsjbsja❀赛博监护人@hg3551019177402✿永远纪念@wu_si787878❀✟",
        "entities": {
          "description": {
            "mentions": [
              {
                "end": 100,
                "start": 89,
                "username": "Fislonely_"
              },
              {
                "end": 114,
                "start": 103,
                "username": "dbdbsjbsja"
              },
              {
                "end": 136,
                "start": 120,
                "username": "hg3551019177402"
              },
              {
                "end": 153,
                "start": 141,
                "username": "wu_si787878"
              }
            ]
          },
          "url": {
            "urls": [
              {
                "display_url": "ngl.link/iirin53261",
                "end": 23,
                "expanded_url": "https://ngl.link/iirin53261",
                "start": 0,
                "url": "https://t.co/1rBZJU4xmt"
              }
            ]
          }
        },
        "id": "2032033299980566528",
        "location": "你看看你身后",
        "name": "霖（完全病娇邪恶中2.0）",
        "pinned_tweet_id": "2038261710612729866",
        "profile_image_url": "https://pbs.twimg.com/profile_images/2040628695006892034/S1_Zc8ek_normal.jpg",
        "protected": false,
        "public_metrics": {
          "followers_count": 754,
          "following_count": 354,
          "like_count": 2289,
          "listed_count": 5,
          "media_count": 68,
          "tweet_count": 1463
        },
        "url": "https://t.co/1rBZJU4xmt",
        "username": "rinii165892",
        "verified": false
      },
      {
        "created_at": "2026-03-11T12:53:23.000Z",
        "description": "sb msk wcnm \n@rinii165892 的最强嘴替 缓慢回fo",
        "entities": {
          "description": {
            "mentions": [
              {
                "end": 25,
                "start": 13,
                "username": "rinii165892"
              }
            ]
          }
        },
        "id": "2031715041196875776",
        "location": "msk坟头",
        "name": "2.雨木木（完全仇恨邪恶msk）",
        "pinned_tweet_id": "2040146886708109777",
        "profile_image_url": "https://pbs.twimg.com/profile_images/2031760424920883200/DV4uG4Xo_normal.jpg",
        "protected": false,
        "public_metrics": {
          "followers_count": 358,
          "following_count": 96,
          "like_count": 283,
          "listed_count": 0,
          "media_count": 8,
          "tweet_count": 281
        },
        "username": "wu_si114514",
        "verified": false
      }
    ]
  }
}