{
  "data": {
    "article": {},
    "attachments": {},
    "author_id": "2008812080099672064",
    "conversation_id": "2040080078974157145",
    "created_at": "2026-04-03T20:04:40.000Z",
    "edit_controls": {
      "editable_until": "2026-04-03T21:04:40.000Z",
      "edits_remaining": 5,
      "is_edit_eligible": false
    },
    "edit_history_tweet_ids": [
      "2040158563876909396"
    ],
    "entities": {
      "mentions": [
        {
          "end": 13,
          "id": "1808604308163940352",
          "start": 0,
          "username": "cici20120712"
        }
      ]
    },
    "geo": {},
    "id": "2040158563876909396",
    "in_reply_to_user_id": "1808604308163940352",
    "lang": "zh",
    "note_tweet": {
      "entities": {}
    },
    "possibly_sensitive": false,
    "public_metrics": {
      "bookmark_count": 0,
      "impression_count": 0,
      "like_count": 1,
      "quote_count": 0,
      "reply_count": 0,
      "retweet_count": 0
    },
    "referenced_tweets": [
      {
        "id": "2040080078974157145",
        "type": "replied_to"
      }
    ],
    "reply_settings": "everyone",
    "text": "@cici20120712 看到一半瞬间笑不出来了 因为我就是这样（悲）"
  },
  "includes": {
    "tweets": [
      {
        "article": {},
        "attachments": {},
        "author_id": "2008812080099672064",
        "conversation_id": "2040080078974157145",
        "created_at": "2026-04-03T20:04:40.000Z",
        "edit_controls": {
          "editable_until": "2026-04-03T21:04:40.000Z",
          "edits_remaining": 5,
          "is_edit_eligible": false
        },
        "edit_history_tweet_ids": [
          "2040158563876909396"
        ],
        "entities": {
          "mentions": [
            {
              "end": 13,
              "id": "1808604308163940352",
              "start": 0,
              "username": "cici20120712"
            }
          ]
        },
        "geo": {},
        "id": "2040158563876909396",
        "in_reply_to_user_id": "1808604308163940352",
        "lang": "zh",
        "note_tweet": {
          "entities": {}
        },
        "possibly_sensitive": false,
        "public_metrics": {
          "bookmark_count": 0,
          "impression_count": 0,
          "like_count": 1,
          "quote_count": 0,
          "reply_count": 0,
          "retweet_count": 0
        },
        "referenced_tweets": [
          {
            "id": "2040080078974157145",
            "type": "replied_to"
          }
        ],
        "reply_settings": "everyone",
        "text": "@cici20120712 看到一半瞬间笑不出来了 因为我就是这样（悲）"
      },
      {
        "article": {},
        "attachments": {},
        "author_id": "1808604308163940352",
        "conversation_id": "2040080078974157145",
        "created_at": "2026-04-03T14:52:48.000Z",
        "edit_controls": {
          "editable_until": "2026-04-03T15:52:48.000Z",
          "edits_remaining": 5,
          "is_edit_eligible": true
        },
        "edit_history_tweet_ids": [
          "2040080078974157145"
        ],
        "entities": {},
        "geo": {},
        "id": "2040080078974157145",
        "lang": "zh",
        "note_tweet": {
          "entities": {}
        },
        "possibly_sensitive": false,
        "public_metrics": {
          "bookmark_count": 61,
          "impression_count": 94657,
          "like_count": 503,
          "quote_count": 24,
          "reply_count": 80,
          "retweet_count": 17
        },
        "reply_settings": "everyone",
        "text": "你知道吗，如果男孩子小时候不是手冲出来的是压床出来的，长大了就会变成小男娘"
      }
    ],
    "users": [
      {
        "created_at": "2026-01-07T08:05:14.000Z",
        "description": "如果你觉得我的负面情绪影响到你 我向你道歉｜ISFP-T｜或许是一只MTX｜OverDose｜无雷｜不见证不割手｜重度社恐｜重抑中焦｜友跨喵🏳️‍⚧️｜可以找我互fo/聊天❤️｜生日：100324｜@NiaoYou83766是小号喵｜好姐姐@Sankta_AM",
        "entities": {
          "description": {
            "mentions": [
              {
                "end": 112,
                "start": 99,
                "username": "NiaoYou83766"
              },
              {
                "end": 130,
                "start": 120,
                "username": "Sankta_AM"
              }
            ]
          },
          "url": {
            "urls": [
              {
                "display_url": "github.com/xiaoyi-0324",
                "end": 23,
                "expanded_url": "https://github.com/xiaoyi-0324",
                "start": 0,
                "url": "https://t.co/0xWsTSdTii"
              }
            ]
          }
        },
        "id": "2008812080099672064",
        "location": "来玩捉迷藏吧？",
        "name": "樱川由奈🏳️‍⚧️sakura",
        "pinned_tweet_id": "2022754784072339931",
        "profile_image_url": "https://pbs.twimg.com/profile_images/2039652543136194560/agP5b8Sq_normal.jpg",
        "protected": false,
        "public_metrics": {
          "followers_count": 108,
          "following_count": 85,
          "like_count": 632,
          "listed_count": 0,
          "media_count": 90,
          "tweet_count": 479
        },
        "url": "https://t.co/0xWsTSdTii",
        "username": "Xiaoyi_0324",
        "verified": false
      },
      {
        "created_at": "2024-07-03T20:50:59.000Z",
        "description": "门槛68zfb口令就行了喵\n底边coser，偶尔会配音或者画画，大部分时间在睡觉，小号@ci20120712",
        "entities": {
          "description": {
            "mentions": [
              {
                "end": 54,
                "start": 43,
                "username": "ci20120712"
              }
            ]
          }
        },
        "id": "1808604308163940352",
        "name": "魔法少女凛瓷瓷",
        "pinned_tweet_id": "2006526827796586753",
        "profile_image_url": "https://pbs.twimg.com/profile_images/1831679763368353792/JCLSUlMG_normal.jpg",
        "protected": false,
        "public_metrics": {
          "followers_count": 70150,
          "following_count": 102,
          "like_count": 858,
          "listed_count": 181,
          "media_count": 731,
          "tweet_count": 1311
        },
        "username": "cici20120712",
        "verified": false
      }
    ]
  }
}