{
  "data": {
    "article": {},
    "attachments": {},
    "author_id": "2008812080099672064",
    "conversation_id": "2052347831026090283",
    "created_at": "2026-05-07T13:14:17.000Z",
    "edit_controls": {
      "editable_until": "2026-05-07T14:14:17.000Z",
      "edits_remaining": 5,
      "is_edit_eligible": false
    },
    "edit_history_tweet_ids": [
      "2052376474016190897"
    ],
    "entities": {
      "mentions": [
        {
          "end": 10,
          "id": "2031715041196875776",
          "start": 0,
          "username": "YiJin_0v0"
        }
      ]
    },
    "geo": {},
    "id": "2052376474016190897",
    "in_reply_to_user_id": "2031715041196875776",
    "lang": "zh",
    "note_tweet": {
      "entities": {}
    },
    "possibly_sensitive": false,
    "public_metrics": {
      "bookmark_count": 0,
      "impression_count": 0,
      "like_count": 0,
      "quote_count": 0,
      "reply_count": 0,
      "retweet_count": 0
    },
    "referenced_tweets": [
      {
        "id": "2052347831026090283",
        "type": "replied_to"
      }
    ],
    "reply_settings": "everyone",
    "text": "@YiJin_0v0 可爱还带点抽象的头像www 好像平等的创飞世界每一个人（ ）"
  },
  "includes": {
    "media": [
      {
        "height": 400,
        "media_key": "3_2052347824894046208",
        "public_metrics": {},
        "type": "photo",
        "url": "https://pbs.twimg.com/media/HHtneRJa8AA_aKm.jpg",
        "width": 400
      }
    ],
    "tweets": [
      {
        "article": {},
        "attachments": {},
        "author_id": "2008812080099672064",
        "conversation_id": "2052347831026090283",
        "created_at": "2026-05-07T13:14:17.000Z",
        "edit_controls": {
          "editable_until": "2026-05-07T14:14:17.000Z",
          "edits_remaining": 5,
          "is_edit_eligible": false
        },
        "edit_history_tweet_ids": [
          "2052376474016190897"
        ],
        "entities": {
          "mentions": [
            {
              "end": 10,
              "id": "2031715041196875776",
              "start": 0,
              "username": "YiJin_0v0"
            }
          ]
        },
        "geo": {},
        "id": "2052376474016190897",
        "in_reply_to_user_id": "2031715041196875776",
        "lang": "zh",
        "note_tweet": {
          "entities": {}
        },
        "possibly_sensitive": false,
        "public_metrics": {
          "bookmark_count": 0,
          "impression_count": 0,
          "like_count": 0,
          "quote_count": 0,
          "reply_count": 0,
          "retweet_count": 0
        },
        "referenced_tweets": [
          {
            "id": "2052347831026090283",
            "type": "replied_to"
          }
        ],
        "reply_settings": "everyone",
        "text": "@YiJin_0v0 可爱还带点抽象的头像www 好像平等的创飞世界每一个人（ ）"
      },
      {
        "article": {},
        "attachments": {
          "media_keys": [
            "3_2052347824894046208"
          ]
        },
        "author_id": "2031715041196875776",
        "conversation_id": "2052347831026090283",
        "created_at": "2026-05-07T11:20:28.000Z",
        "edit_controls": {
          "editable_until": "2026-05-07T12:20:28.000Z",
          "edits_remaining": 5,
          "is_edit_eligible": true
        },
        "edit_history_tweet_ids": [
          "2052347831026090283"
        ],
        "entities": {
          "hashtags": [
            {
              "end": 4,
              "start": 0,
              "tag": "新头像"
            }
          ],
          "urls": [
            {
              "display_url": "pic.x.com/rTlKkdPGmR",
              "end": 28,
              "expanded_url": "https://x.com/YiJin_0v0/status/2052347831026090283/photo/1",
              "media_key": "3_2052347824894046208",
              "start": 5,
              "url": "https://t.co/rTlKkdPGmR"
            }
          ]
        },
        "geo": {},
        "id": "2052347831026090283",
        "lang": "qme",
        "note_tweet": {
          "entities": {}
        },
        "possibly_sensitive": false,
        "public_metrics": {
          "bookmark_count": 0,
          "impression_count": 612,
          "like_count": 68,
          "quote_count": 0,
          "reply_count": 7,
          "retweet_count": 0
        },
        "reply_settings": "everyone",
        "text": "#新头像 https://t.co/rTlKkdPGmR"
      }
    ],
    "users": [
      {
        "created_at": "2026-01-07T08:05:14.000Z",
        "description": "几乎全天在线的互联网飞舞!负面情绪/碎碎念致歉|半日常推|直fo成分回|同类直接回(没看到要私信🥹|MTX(F?)|出柜:26/4/30|好东西都在这个号👉@NiaoYou83766😋|⬇️匿名提问|二代目:@Johnsons8nx",
        "entities": {
          "description": {
            "mentions": [
              {
                "end": 91,
                "start": 78,
                "username": "NiaoYou83766"
              },
              {
                "end": 116,
                "start": 104,
                "username": "Johnsons8nx"
              }
            ]
          },
          "url": {
            "urls": [
              {
                "display_url": "ngl.link/xiaoyi0324",
                "end": 23,
                "expanded_url": "https://ngl.link/xiaoyi0324",
                "start": 0,
                "url": "https://t.co/SiMjjU6DSn"
              }
            ]
          }
        },
        "id": "2008812080099672064",
        "location": "来玩捉迷藏吧？",
        "name": "樱川由奈🏳️‍⚧️Sakura🍥",
        "pinned_tweet_id": "2049988057991119193",
        "profile_image_url": "https://pbs.twimg.com/profile_images/2041966864163880960/7aHicZzs_normal.jpg",
        "protected": false,
        "public_metrics": {
          "followers_count": 487,
          "following_count": 217,
          "like_count": 1343,
          "listed_count": 2,
          "media_count": 179,
          "tweet_count": 1377
        },
        "url": "https://t.co/SiMjjU6DSn",
        "username": "Xiaoyi_0324",
        "verified": false
      },
      {
        "created_at": "2026-03-11T12:53:23.000Z",
        "description": "3.0 笑死我了\n不发帖就是犯病了（没有说发帖就不犯病的意思）\n多动-精分-双向-已放弃治疗🥳/缓慢回fo，整理账号\n永远纪念 @iirin_0917^@wu_si787878\n随时附身@Melody_0v0_",
        "entities": {
          "description": {
            "mentions": [
              {
                "end": 75,
                "start": 64,
                "username": "iirin_0917"
              },
              {
                "end": 88,
                "start": 76,
                "username": "wu_si787878"
              },
              {
                "end": 105,
                "start": 93,
                "username": "Melody_0v0_"
              }
            ]
          }
        },
        "id": "2031715041196875776",
        "location": "你看看你身后",
        "name": "3.霖（完全病娇邪恶中二）",
        "pinned_tweet_id": "2052349093230629151",
        "profile_image_url": "https://pbs.twimg.com/profile_images/2052347801045200896/4j5q_ZbS_normal.jpg",
        "protected": false,
        "public_metrics": {
          "followers_count": 786,
          "following_count": 590,
          "like_count": 5409,
          "listed_count": 2,
          "media_count": 142,
          "tweet_count": 3026
        },
        "username": "YiJin_0v0",
        "verified": false
      }
    ]
  }
}