{
  "data": {
    "article": {},
    "attachments": {
      "media_keys": [
        "3_2050270311451639809"
      ]
    },
    "author_id": "2008812080099672064",
    "conversation_id": "2050270319798353963",
    "created_at": "2026-05-01T17:45:11.000Z",
    "edit_controls": {
      "editable_until": "2026-05-01T18:45:11.000Z",
      "edits_remaining": 5,
      "is_edit_eligible": true
    },
    "edit_history_tweet_ids": [
      "2050270319798353963"
    ],
    "entities": {
      "urls": [
        {
          "display_url": "pic.x.com/AxM7afAIXg",
          "end": 32,
          "expanded_url": "https://x.com/Xiaoyi_0324/status/2050270319798353963/photo/1",
          "media_key": "3_2050270311451639809",
          "start": 9,
          "url": "https://t.co/AxM7afAIXg"
        }
      ]
    },
    "geo": {},
    "id": "2050270319798353963",
    "lang": "zh",
    "note_tweet": {
      "entities": {}
    },
    "possibly_sensitive": false,
    "public_metrics": {
      "bookmark_count": 0,
      "impression_count": 0,
      "like_count": 0,
      "quote_count": 0,
      "reply_count": 0,
      "retweet_count": 0
    },
    "reply_settings": "everyone",
    "text": "дёҚеҮҶеҒ·жҲ‘зҡ„жүӢжңәрҹҳЎ https://t.co/AxM7afAIXg"
  },
  "includes": {
    "media": [
      {
        "height": 2527,
        "media_key": "3_2050270311451639809",
        "public_metrics": {},
        "type": "photo",
        "url": "https://pbs.twimg.com/media/HHQF_EeawAEKasZ.jpg",
        "width": 1179
      }
    ],
    "tweets": [
      {
        "article": {},
        "attachments": {
          "media_keys": [
            "3_2050270311451639809"
          ]
        },
        "author_id": "2008812080099672064",
        "conversation_id": "2050270319798353963",
        "created_at": "2026-05-01T17:45:11.000Z",
        "edit_controls": {
          "editable_until": "2026-05-01T18:45:11.000Z",
          "edits_remaining": 5,
          "is_edit_eligible": true
        },
        "edit_history_tweet_ids": [
          "2050270319798353963"
        ],
        "entities": {
          "urls": [
            {
              "display_url": "pic.x.com/AxM7afAIXg",
              "end": 32,
              "expanded_url": "https://x.com/Xiaoyi_0324/status/2050270319798353963/photo/1",
              "media_key": "3_2050270311451639809",
              "start": 9,
              "url": "https://t.co/AxM7afAIXg"
            }
          ]
        },
        "geo": {},
        "id": "2050270319798353963",
        "lang": "zh",
        "note_tweet": {
          "entities": {}
        },
        "possibly_sensitive": false,
        "public_metrics": {
          "bookmark_count": 0,
          "impression_count": 0,
          "like_count": 0,
          "quote_count": 0,
          "reply_count": 0,
          "retweet_count": 0
        },
        "reply_settings": "everyone",
        "text": "дёҚеҮҶеҒ·жҲ‘зҡ„жүӢжңәрҹҳЎ https://t.co/AxM7afAIXg"
      }
    ],
    "users": [
      {
        "created_at": "2026-01-07T08:05:14.000Z",
        "description": "еҮ д№Һе…ЁеӨ©еңЁзәҝзҡ„дә’иҒ”зҪ‘йЈһиҲһ!иҙҹйқўжғ…з»Ә/зўҺзўҺеҝөиҮҙжӯү|еҚҠж—ҘеёёжҺЁ|зӣҙfoжҲҗеҲҶеӣһ|еҗҢзұ»зӣҙжҺҘеӣһ(жІЎзңӢеҲ°иҰҒз§ҒдҝЎрҹҘ№|MTX(F?)|еҘҪдёңиҘҝйғҪеңЁиҝҷдёӘеҸ·рҹ‘ү@NiaoYou83766рҹҳӢ|дәҢд»Јзӣ®:@Johnsons8nx|в¬ҮпёҸеҢҝеҗҚжҸҗй—®",
        "entities": {
          "description": {
            "mentions": [
              {
                "end": 80,
                "start": 67,
                "username": "NiaoYou83766"
              },
              {
                "end": 98,
                "start": 86,
                "username": "Johnsons8nx"
              }
            ]
          },
          "url": {
            "urls": [
              {
                "display_url": "ngl.link/xiaoyi0324",
                "end": 23,
                "expanded_url": "https://ngl.link/xiaoyi0324",
                "start": 0,
                "url": "https://t.co/SiMjjU6DSn"
              }
            ]
          }
        },
        "id": "2008812080099672064",
        "location": "жқҘзҺ©жҚүиҝ·и—Ҹеҗ§пјҹ",
        "name": "жЁұе·қз”ұеҘҲрҹҸіпёҸвҖҚвҡ§пёҸSakuraрҹҚҘ",
        "pinned_tweet_id": "2049988057991119193",
        "profile_image_url": "https://pbs.twimg.com/profile_images/2041966864163880960/7aHicZzs_normal.jpg",
        "protected": false,
        "public_metrics": {
          "followers_count": 429,
          "following_count": 196,
          "like_count": 1209,
          "listed_count": 0,
          "media_count": 167,
          "tweet_count": 1216
        },
        "url": "https://t.co/SiMjjU6DSn",
        "username": "Xiaoyi_0324",
        "verified": false
      }
    ]
  }
}