{
  "data": {
    "article": {},
    "attachments": {},
    "author_id": "2008812080099672064",
    "conversation_id": "2069436262449328397",
    "created_at": "2026-06-28T16:37:44.000Z",
    "edit_controls": {
      "editable_until": "2026-06-28T17:37:44.000Z",
      "edits_remaining": 5,
      "is_edit_eligible": false
    },
    "edit_history_tweet_ids": [
      "2071271845081571482"
    ],
    "entities": {
      "mentions": [
        {
          "end": 10,
          "id": "1995266194576961536",
          "start": 0,
          "username": "skyseafor"
        },
        {
          "end": 21,
          "id": "1659962043460354050",
          "start": 11,
          "username": "SalviaSWC"
        }
      ]
    },
    "geo": {},
    "id": "2071271845081571482",
    "in_reply_to_user_id": "1995266194576961536",
    "lang": "zh",
    "note_tweet": {
      "entities": {}
    },
    "possibly_sensitive": false,
    "public_metrics": {
      "bookmark_count": 0,
      "impression_count": 0,
      "like_count": 0,
      "quote_count": 0,
      "reply_count": 0,
      "retweet_count": 0
    },
    "referenced_tweets": [
      {
        "id": "2069436262449328397",
        "type": "replied_to"
      }
    ],
    "reply_settings": "everyone",
    "text": "@skyseafor @SalviaSWC ai给我ai好了呀 头发这么长一点也不ooc"
  },
  "includes": {
    "media": [
      {
        "height": 1254,
        "media_key": "3_2069436259731451904",
        "public_metrics": {},
        "type": "photo",
        "url": "https://pbs.twimg.com/media/HLgdUFqbMAAytuf.jpg",
        "width": 1254
      }
    ],
    "tweets": [
      {
        "article": {},
        "attachments": {},
        "author_id": "2008812080099672064",
        "conversation_id": "2069436262449328397",
        "created_at": "2026-06-28T16:37:44.000Z",
        "edit_controls": {
          "editable_until": "2026-06-28T17:37:44.000Z",
          "edits_remaining": 5,
          "is_edit_eligible": false
        },
        "edit_history_tweet_ids": [
          "2071271845081571482"
        ],
        "entities": {
          "mentions": [
            {
              "end": 10,
              "id": "1995266194576961536",
              "start": 0,
              "username": "skyseafor"
            },
            {
              "end": 21,
              "id": "1659962043460354050",
              "start": 11,
              "username": "SalviaSWC"
            }
          ]
        },
        "geo": {},
        "id": "2071271845081571482",
        "in_reply_to_user_id": "1995266194576961536",
        "lang": "zh",
        "note_tweet": {
          "entities": {}
        },
        "possibly_sensitive": false,
        "public_metrics": {
          "bookmark_count": 0,
          "impression_count": 0,
          "like_count": 0,
          "quote_count": 0,
          "reply_count": 0,
          "retweet_count": 0
        },
        "referenced_tweets": [
          {
            "id": "2069436262449328397",
            "type": "replied_to"
          }
        ],
        "reply_settings": "everyone",
        "text": "@skyseafor @SalviaSWC ai给我ai好了呀 头发这么长一点也不ooc"
      },
      {
        "article": {},
        "attachments": {
          "media_keys": [
            "3_2069436259731451904"
          ]
        },
        "author_id": "1995266194576961536",
        "conversation_id": "2069436262449328397",
        "created_at": "2026-06-23T15:03:47.000Z",
        "edit_controls": {
          "editable_until": "2026-06-23T16:03:47.000Z",
          "edits_remaining": 5,
          "is_edit_eligible": true
        },
        "edit_history_tweet_ids": [
          "2069436262449328397"
        ],
        "entities": {
          "urls": [
            {
              "display_url": "pic.x.com/lDrF2qWxS6",
              "end": 36,
              "expanded_url": "https://x.com/skyseafor/status/2069436262449328397/photo/1",
              "media_key": "3_2069436259731451904",
              "start": 13,
              "url": "https://t.co/lDrF2qWxS6"
            },
            {
              "display_url": "x.com/skyseafor/stat…",
              "end": 60,
              "expanded_url": "https://twitter.com/skyseafor/status/2067464795075584100",
              "start": 37,
              "url": "https://t.co/0BUoegpDuw"
            }
          ]
        },
        "geo": {},
        "id": "2069436262449328397",
        "lang": "zh",
        "note_tweet": {
          "entities": {}
        },
        "possibly_sensitive": false,
        "public_metrics": {
          "bookmark_count": 0,
          "impression_count": 7145,
          "like_count": 57,
          "quote_count": 2,
          "reply_count": 19,
          "retweet_count": 1
        },
        "referenced_tweets": [
          {
            "id": "2067464795075584100",
            "type": "quoted"
          }
        ],
        "reply_settings": "everyone",
        "text": "冰棍现在的表情是这样子的 https://t.co/lDrF2qWxS6 https://t.co/0BUoegpDuw"
      }
    ],
    "users": [
      {
        "created_at": "2026-01-07T08:05:14.000Z",
        "description": "几乎全天在线的互联网飞舞|爱人:@YuChenawa|亮点里是我个人精选帖😋|里推@Ruai_0324|MTF|出柜:26/4/30|家长不管党?|无证含糖:26/5/26|直fo成分回|只互同类|其他互fo请私信|我们的项目:@TransCircleOrg|",
        "entities": {
          "description": {
            "mentions": [
              {
                "end": 26,
                "start": 16,
                "username": "YuChenawa"
              },
              {
                "end": 51,
                "start": 41,
                "username": "Ruai_0324"
              },
              {
                "end": 129,
                "start": 114,
                "username": "TransCircleOrg"
              }
            ]
          },
          "url": {
            "urls": [
              {
                "display_url": "ngl.link/xiaoyi_0324",
                "end": 23,
                "expanded_url": "https://ngl.link/xiaoyi_0324",
                "start": 0,
                "url": "https://t.co/KVsMyBLR77"
              }
            ]
          }
        },
        "id": "2008812080099672064",
        "location": "⬇️求求你了来玩提問箱吧➡️",
        "name": "櫻川由奈🏳️‍⚧️Sakura🍥",
        "pinned_tweet_id": "2059891753067659361",
        "profile_image_url": "https://pbs.twimg.com/profile_images/2041966864163880960/7aHicZzs_normal.jpg",
        "protected": false,
        "public_metrics": {
          "followers_count": 1333,
          "following_count": 378,
          "like_count": 1803,
          "listed_count": 4,
          "media_count": 330,
          "tweet_count": 2732
        },
        "url": "https://t.co/KVsMyBLR77",
        "username": "Xiaoyi_0324",
        "verified": true
      },
      {
        "created_at": "2025-11-30T22:58:47.000Z",
        "description": "原号被封禁了@520illusion \n/ 永远的南京城 / 08 / 许你岁岁平安 / 请不要查我的成分/ 不是女生 / 可我喜欢你 / crypto / 直男勿扰 我的门槛你过不起",
        "entities": {
          "description": {
            "mentions": [
              {
                "end": 18,
                "start": 6,
                "username": "520illusion"
              }
            ]
          }
        },
        "id": "1995266194576961536",
        "location": "宁波大学医学院",
        "name": "sky ill",
        "pinned_tweet_id": "2069767708934332850",
        "profile_image_url": "https://pbs.twimg.com/profile_images/2062149149957718016/xZjcwonh_normal.jpg",
        "protected": false,
        "public_metrics": {
          "followers_count": 1214,
          "following_count": 205,
          "like_count": 852,
          "listed_count": 2,
          "media_count": 260,
          "tweet_count": 576
        },
        "url": "",
        "username": "skyseafor",
        "verified": true
      },
      {
        "created_at": "2023-05-20T16:39:35.000Z",
        "description": "非必要不键政🏳️|不卖药🚫|欢迎任何人🌈|包容各种做法☮|互fo🉑🥰|没回fo的话，请私信我哦📬|\n\n脑婆:@DXM8964LXM\n\n丨药物知识开源化💊|来FreeODwiki看看吧！https://t.co/ki2TerCl7C |Say Know to Drugs 😼",
        "entities": {
          "description": {
            "mentions": [
              {
                "end": 65,
                "start": 54,
                "username": "DXM8964LXM"
              }
            ],
            "urls": [
              {
                "display_url": "github.com/SalviaSWC/Free…",
                "end": 115,
                "expanded_url": "https://github.com/SalviaSWC/FreeODwiki",
                "start": 92,
                "url": "https://t.co/ki2TerCl7C"
              }
            ]
          },
          "url": {
            "urls": [
              {
                "display_url": "freeodwiki.org",
                "end": 23,
                "expanded_url": "https://freeodwiki.org",
                "start": 0,
                "url": "https://t.co/20q0OtAeQd"
              }
            ]
          }
        },
        "id": "1659962043460354050",
        "name": "鼠尾草～🌿",
        "profile_image_url": "https://pbs.twimg.com/profile_images/2034583473692852224/nE4xPVUJ_normal.jpg",
        "protected": false,
        "public_metrics": {
          "followers_count": 4970,
          "following_count": 1031,
          "like_count": 24787,
          "listed_count": 11,
          "media_count": 566,
          "tweet_count": 7982
        },
        "url": "https://t.co/20q0OtAeQd",
        "username": "SalviaSWC",
        "verified": false
      }
    ]
  }
}