{
  "data": {
    "article": {},
    "attachments": {
      "media_keys": [
        "3_2059592745526956032"
      ]
    },
    "author_id": "2008812080099672064",
    "conversation_id": "2059556726391914988",
    "created_at": "2026-05-27T11:09:11.000Z",
    "edit_controls": {
      "editable_until": "2026-05-27T12:09:11.000Z",
      "edits_remaining": 5,
      "is_edit_eligible": false
    },
    "edit_history_tweet_ids": [
      "2059592751185109137"
    ],
    "entities": {
      "mentions": [
        {
          "end": 12,
          "id": "2040516492479823872",
          "start": 0,
          "username": "Verdin14shi"
        }
      ],
      "urls": [
        {
          "display_url": "x.com/ruai_0324/stat…",
          "end": 36,
          "expanded_url": "https://x.com/ruai_0324/status/2059378997960847686?s=46",
          "start": 13,
          "url": "https://t.co/I5d3GymlxR"
        },
        {
          "display_url": "pic.x.com/rEeXjuQByO",
          "end": 81,
          "expanded_url": "https://x.com/Xiaoyi_0324/status/2059592751185109137/photo/1",
          "media_key": "3_2059592745526956032",
          "start": 58,
          "url": "https://t.co/rEeXjuQByO"
        }
      ]
    },
    "geo": {},
    "id": "2059592751185109137",
    "in_reply_to_user_id": "2040516492479823872",
    "lang": "ja",
    "note_tweet": {
      "entities": {}
    },
    "possibly_sensitive": false,
    "public_metrics": {
      "bookmark_count": 0,
      "impression_count": 0,
      "like_count": 0,
      "quote_count": 0,
      "reply_count": 0,
      "retweet_count": 0
    },
    "referenced_tweets": [
      {
        "id": "2059378997960847686",
        "type": "quoted"
      },
      {
        "id": "2059556726391914988",
        "type": "replied_to"
      }
    ],
    "reply_settings": "everyone",
    "text": "@Verdin14shi https://t.co/I5d3GymlxR\n你下面就是她 看笑了 也給我block了 https://t.co/rEeXjuQByO"
  },
  "includes": {
    "media": [
      {
        "height": 2048,
        "media_key": "3_2059592745526956032",
        "public_metrics": {},
        "type": "photo",
        "url": "https://pbs.twimg.com/media/HJUksJsbEAA3aEw.jpg",
        "width": 945
      },
      {
        "height": 2800,
        "media_key": "3_2059378995154804736",
        "public_metrics": {},
        "type": "photo",
        "url": "https://pbs.twimg.com/media/HJRiSPgaYAA0GpX.jpg",
        "width": 1272
      },
      {
        "height": 2018,
        "media_key": "3_2059556713150472192",
        "public_metrics": {},
        "type": "photo",
        "url": "https://pbs.twimg.com/media/HJUD6yoa4AAJnlA.jpg",
        "width": 1156
      }
    ],
    "tweets": [
      {
        "article": {},
        "attachments": {
          "media_keys": [
            "3_2059592745526956032"
          ]
        },
        "author_id": "2008812080099672064",
        "conversation_id": "2059556726391914988",
        "created_at": "2026-05-27T11:09:11.000Z",
        "edit_controls": {
          "editable_until": "2026-05-27T12:09:11.000Z",
          "edits_remaining": 5,
          "is_edit_eligible": false
        },
        "edit_history_tweet_ids": [
          "2059592751185109137"
        ],
        "entities": {
          "mentions": [
            {
              "end": 12,
              "id": "2040516492479823872",
              "start": 0,
              "username": "Verdin14shi"
            }
          ],
          "urls": [
            {
              "display_url": "x.com/ruai_0324/stat…",
              "end": 36,
              "expanded_url": "https://x.com/ruai_0324/status/2059378997960847686?s=46",
              "start": 13,
              "url": "https://t.co/I5d3GymlxR"
            },
            {
              "display_url": "pic.x.com/rEeXjuQByO",
              "end": 81,
              "expanded_url": "https://x.com/Xiaoyi_0324/status/2059592751185109137/photo/1",
              "media_key": "3_2059592745526956032",
              "start": 58,
              "url": "https://t.co/rEeXjuQByO"
            }
          ]
        },
        "geo": {},
        "id": "2059592751185109137",
        "in_reply_to_user_id": "2040516492479823872",
        "lang": "ja",
        "note_tweet": {
          "entities": {}
        },
        "possibly_sensitive": false,
        "public_metrics": {
          "bookmark_count": 0,
          "impression_count": 0,
          "like_count": 0,
          "quote_count": 0,
          "reply_count": 0,
          "retweet_count": 0
        },
        "referenced_tweets": [
          {
            "id": "2059378997960847686",
            "type": "quoted"
          },
          {
            "id": "2059556726391914988",
            "type": "replied_to"
          }
        ],
        "reply_settings": "everyone",
        "text": "@Verdin14shi https://t.co/I5d3GymlxR\n你下面就是她 看笑了 也給我block了 https://t.co/rEeXjuQByO"
      },
      {
        "article": {},
        "attachments": {
          "media_keys": [
            "3_2059378995154804736"
          ]
        },
        "author_id": "2055228634710065152",
        "conversation_id": "2059378997960847686",
        "created_at": "2026-05-26T20:59:49.000Z",
        "edit_controls": {
          "editable_until": "2026-05-26T21:59:49.000Z",
          "edits_remaining": 5,
          "is_edit_eligible": false
        },
        "edit_history_tweet_ids": [
          "2059378997960847686"
        ],
        "entities": {
          "mentions": [
            {
              "end": 13,
              "id": "1962302660541079552",
              "start": 5,
              "username": "yuerQwQ"
            }
          ],
          "urls": [
            {
              "display_url": "pic.x.com/tomFBvJpuj",
              "end": 114,
              "expanded_url": "https://x.com/Ruai_0324/status/2059378997960847686/photo/1",
              "media_key": "3_2059378995154804736",
              "start": 91,
              "url": "https://t.co/tomFBvJpuj"
            }
          ]
        },
        "geo": {},
        "id": "2059378997960847686",
        "lang": "zh",
        "note_tweet": {
          "entities": {}
        },
        "possibly_sensitive": false,
        "public_metrics": {
          "bookmark_count": 0,
          "impression_count": 115,
          "like_count": 1,
          "quote_count": 1,
          "reply_count": 1,
          "retweet_count": 0
        },
        "reply_settings": "everyone",
        "text": "這集神了\n@yuerQwQ …？你咋給我誤傷了\n你從哪裡發現我和tyw關係不錯的？\n還是說 你block我另有其因(๑•̌.•̑๑)ˀ̣ˀ̣\n我是不了解的 我QQ上沒少罵tyw啊🫪 https://t.co/tomFBvJpuj"
      },
      {
        "article": {},
        "attachments": {
          "media_keys": [
            "3_2059556713150472192"
          ]
        },
        "author_id": "2040516492479823872",
        "conversation_id": "2059556726391914988",
        "created_at": "2026-05-27T08:46:02.000Z",
        "edit_controls": {
          "editable_until": "2026-05-27T09:46:02.000Z",
          "edits_remaining": 5,
          "is_edit_eligible": true
        },
        "edit_history_tweet_ids": [
          "2059556726391914988"
        ],
        "entities": {
          "urls": [
            {
              "display_url": "pic.x.com/TlBUQMHm0z",
              "end": 33,
              "expanded_url": "https://x.com/Verdin14shi/status/2059556726391914988/photo/1",
              "media_key": "3_2059556713150472192",
              "start": 10,
              "url": "https://t.co/TlBUQMHm0z"
            }
          ]
        },
        "geo": {},
        "id": "2059556726391914988",
        "lang": "zh",
        "note_tweet": {
          "entities": {}
        },
        "possibly_sensitive": false,
        "public_metrics": {
          "bookmark_count": 0,
          "impression_count": 272,
          "like_count": 5,
          "quote_count": 0,
          "reply_count": 3,
          "retweet_count": 0
        },
        "reply_settings": "everyone",
        "text": "我才发现？HYW啊 https://t.co/TlBUQMHm0z"
      }
    ],
    "users": [
      {
        "created_at": "2026-01-07T08:05:14.000Z",
        "description": "几乎全天在线的互联网飞舞|直fo成分回|友跨/同类直接回(没看到要私信🥹|MTFTX|出柜:26/4/30|家长不管党?|🍥:26/5/26|碎碎念移步@NiaoYou83766|第二人格:@Ruai_0324|⬇️匿名提問",
        "entities": {
          "description": {
            "mentions": [
              {
                "end": 89,
                "start": 76,
                "username": "NiaoYou83766"
              },
              {
                "end": 105,
                "start": 95,
                "username": "Ruai_0324"
              }
            ]
          },
          "url": {
            "urls": [
              {
                "display_url": "ngl.link/xiaoyi0324",
                "end": 23,
                "expanded_url": "https://ngl.link/xiaoyi0324",
                "start": 0,
                "url": "https://t.co/SiMjjU6DSn"
              }
            ]
          }
        },
        "id": "2008812080099672064",
        "location": "工作郵箱:Ruai@transcircle.org",
        "name": "櫻川由奈🏳️‍⚧️Sakura",
        "pinned_tweet_id": "2057134938068222099",
        "profile_image_url": "https://pbs.twimg.com/profile_images/2041966864163880960/7aHicZzs_normal.jpg",
        "protected": false,
        "public_metrics": {
          "followers_count": 698,
          "following_count": 282,
          "like_count": 1413,
          "listed_count": 4,
          "media_count": 233,
          "tweet_count": 1749
        },
        "url": "https://t.co/SiMjjU6DSn",
        "username": "Xiaoyi_0324",
        "verified": false
      },
      {
        "created_at": "2026-04-04T19:47:30.000Z",
        "description": "2012|07|15 INFP 心理性别女？ 175l65kg（欢迎赛博性骚扰，不许发那种图片） 双性恋  暂辍学在家 此账号为善良人格，不知何时病变  我会关注所有有趣或可怜可爱的人喵，你们的灵魂我很喜欢\n马克思人本主义/民主社会主义\n电子游魂一枚～\n名字翻译过来叫星野柚咲",
        "id": "2040516492479823872",
        "location": "胶东半岛",
        "name": "Hoshine_yosa",
        "pinned_tweet_id": "2058540755430596760",
        "profile_image_url": "https://pbs.twimg.com/profile_images/2057722947754934272/HXjj-Ag2_normal.jpg",
        "protected": false,
        "public_metrics": {
          "followers_count": 456,
          "following_count": 473,
          "like_count": 822,
          "listed_count": 1,
          "media_count": 23,
          "tweet_count": 1218
        },
        "username": "Verdin14shi",
        "verified": true
      },
      {
        "created_at": "2026-05-15T10:08:54.000Z",
        "description": "櫻川由奈的另一個人格Ruai(@xiaoyi_0324)|簡中/繁中🉑|造物日:10/3/24 垃圾桶:@NiaoYou83766",
        "entities": {
          "description": {
            "mentions": [
              {
                "end": 27,
                "start": 15,
                "username": "xiaoyi_0324"
              },
              {
                "end": 65,
                "start": 52,
                "username": "NiaoYou83766"
              }
            ]
          },
          "url": {
            "urls": [
              {
                "display_url": "t.me/YunaSakagami",
                "end": 23,
                "expanded_url": "https://t.me/YunaSakagami",
                "start": 0,
                "url": "https://t.co/0yW1OEp9Bq"
              }
            ]
          }
        },
        "id": "2055228634710065152",
        "location": "吉林省",
        "name": "Ruai_🏳️‍⚧️",
        "profile_image_url": "https://pbs.twimg.com/profile_images/2055229295052935168/EYY7LEmi_normal.jpg",
        "protected": false,
        "public_metrics": {
          "followers_count": 20,
          "following_count": 17,
          "like_count": 7,
          "listed_count": 0,
          "media_count": 1,
          "tweet_count": 4
        },
        "url": "https://t.co/0yW1OEp9Bq",
        "username": "Ruai_0324",
        "verified": false
      }
    ]
  }
}